nonebot_plugin_manosoba_reply_generator/Utils.py
nonebot_plugin_manosoba_reply_generator/__init__.py
nonebot_plugin_manosoba_reply_generator-0.1.4.dist-info/METADATA
nonebot_plugin_manosoba_reply_generator-0.1.4.dist-info/WHEEL
nonebot_plugin_manosoba_reply_generator-0.1.4.dist-info/top_level.txt
nonebot_plugin_manosoba_reply_generator-0.1.4.dist-info/RECORD
