Metadata-Version: 2.4
Name: nonebot-plugin-manosoba-reply-generator
Version: 0.1.4
Summary: a reply img generator for the game manosoba
Requires-Python: <4.0,>=3.9
Requires-Dist: nonebot2>=2.0.0
Requires-Dist: nonebot-adapter-onebot>=2.0.0
Requires-Dist: pillow>=10.0.0
